MANIFEST.in
parseDockerFile.py
registryClient.py
setup.py
template.xml
bioshadock_biotools/__init__.py
bioshadock_biotools/biotools.py
bioshadock_biotools/parser.py
bioshadock_biotools.egg-info/PKG-INFO
bioshadock_biotools.egg-info/SOURCES.txt
bioshadock_biotools.egg-info/dependency_links.txt
bioshadock_biotools.egg-info/requires.txt
bioshadock_biotools.egg-info/top_level.txt