Metadata-Version: 1.1
Name: bioshadock-biotools
Version: 1.0.1
Summary: Import tool for biotools from Dockerfile
Home-page: UNKNOWN
Author: Francois Moreews
Author-email: UNKNOWN
License: Apache 2.0
Platform: UNKNOWN
Classifier: Programming Language :: Python
Classifier: Development Status :: 5 - Production/Stable
Classifier: License :: OSI Approved :: Apache Software License
Classifier: Natural Language :: English
Classifier: Operating System :: OS Independent
Classifier: Programming Language :: Python :: 2.7
Classifier: Topic :: Communications
